{
    "1": {
        "name": "Barrel Bluff",
        "links": {
            "5": "Vine Defence",
            "3": "Grape Harvest",
            "2": "Oak Enclave",
            "35": "Whetstones"
        }
    },
    "2": {
        "name": "Oak Enclave",
        "links": {
            "1": "Barrel Bluff",
            "3": "Grape Harvest"
        }
    },
    "3": {
        "name": "Grape Harvest",
        "links": {
            "5": "Vine Defence",
            "2": "Oak Enclave",
            "4": "Vines of Wrath",
            "1": "Barrel Bluff"
        }
    },
    "4": {
        "name": "Vines of Wrath",
        "links": {
            "3": "Grape Harvest",
            "7": "West Fjord",
            "5": "Vine Defence"
        }
    },
    "5": {
        "name": "Vine Defence",
        "links": {
            "4": "Vines of Wrath",
            "1": "Barrel Bluff",
            "3": "Grape Harvest",
            "11": "Ride to Valhalla"
        }
    },
    "6": {
        "name": "Hay Meadow ",
        "links": {
            "9": "Brattahlid",
            "7": "West Fjord"
        }
    },
    "7": {
        "name": "West Fjord",
        "links": {
            "4": "Vines of Wrath",
            "6": "Hay Meadow "
        }
    },
    "8": {
        "name": "East Fjord",
        "links": {
            "9": "Brattahlid",
            "19": "Thorfinn"
        }
    },
    "9": {
        "name": "Brattahlid",
        "links": {
            "8": "East Fjord",
            "12": "Lucky Leif",
            "6": "Hay Meadow "
        }
    },
    "10": {
        "name": "Unsinkable",
        "links": {
            "27": "Dried Shallows",
            "24": "Stony Outlook",
            "12": "Lucky Leif"
        }
    },
    "11": {
        "name": "Ride to Valhalla",
        "links": {
            "12": "Lucky Leif",
            "5": "Vine Defence",
            "32": "Fox Burrow"
        }
    },
    "12": {
        "name": "Lucky Leif",
        "links": {
            "11": "Ride to Valhalla",
            "9": "Brattahlid",
            "10": "Unsinkable",
            "13": "Swimming Dutchman"
        }
    },
    "13": {
        "name": "Swimming Dutchman",
        "links": {
            "14": "Valkyries",
            "12": "Lucky Leif",
            "17": "Future Flatpack",
            "25": "Launch Bay"
        }
    },
    "14": {
        "name": "Valkyries",
        "links": {
            "20": "Valley's End",
            "13": "Swimming Dutchman"
        }
    },
    "15": {
        "name": "Ashen Forest",
        "links": {
            "19": "Thorfinn",
            "16": "Log Land"
        }
    },
    "16": {
        "name": "Log Land",
        "links": {
            "19": "Thorfinn",
            "18": "Redwood Refuge",
            "15": "Ashen Forest"
        }
    },
    "17": {
        "name": "Future Flatpack",
        "links": {
            "19": "Thorfinn",
            "18": "Redwood Refuge",
            "13": "Swimming Dutchman"
        }
    },
    "18": {
        "name": "Redwood Refuge",
        "links": {
            "16": "Log Land",
            "17": "Future Flatpack"
        }
    },
    "19": {
        "name": "Thorfinn",
        "links": {
            "16": "Log Land",
            "8": "East Fjord",
            "17": "Future Flatpack",
            "15": "Ashen Forest"
        }
    },
    "20": {
        "name": "Valley's End",
        "links": {
            "14": "Valkyries",
            "22": "Snow Tipped Crop",
            "25": "Launch Bay"
        }
    },
    "21": {
        "name": "Frozen Field",
        "links": {
            "22": "Snow Tipped Crop",
            "25": "Launch Bay"
        }
    },
    "22": {
        "name": "Snow Tipped Crop",
        "links": {
            "25": "Launch Bay",
            "20": "Valley's End",
            "21": "Frozen Field"
        }
    },
    "23": {
        "name": "Frosty Peak",
        "links": {
            "24": "Stony Outlook",
            "25": "Launch Bay"
        }
    },
    "24": {
        "name": "Stony Outlook",
        "links": {
            "23": "Frosty Peak",
            "10": "Unsinkable"
        }
    },
    "25": {
        "name": "Launch Bay",
        "links": {
            "22": "Snow Tipped Crop",
            "23": "Frosty Peak",
            "20": "Valley's End",
            "13": "Swimming Dutchman",
            "21": "Frozen Field"
        }
    },
    "26": {
        "name": "Frozen Creek",
        "links": {
            "28": "Turnip Field",
            "30": "Rocky Ridge"
        }
    },
    "27": {
        "name": "Dried Shallows",
        "links": {
            "10": "Unsinkable",
            "28": "Turnip Field"
        }
    },
    "28": {
        "name": "Turnip Field",
        "links": {
            "27": "Dried Shallows",
            "26": "Frozen Creek"
        }
    },
    "29": {
        "name": "Monolith",
        "links": {
            "34": "Kit Kennel ",
            "32": "Fox Burrow",
            "30": "Rocky Ridge"
        }
    },
    "30": {
        "name": "Rocky Ridge",
        "links": {
            "31": "Obelisk",
            "29": "Monolith",
            "26": "Frozen Creek"
        }
    },
    "31": {
        "name": "Obelisk",
        "links": {
            "32": "Fox Burrow",
            "30": "Rocky Ridge"
        }
    },
    "32": {
        "name": "Fox Burrow",
        "links": {
            "33": "Kernel Keep",
            "31": "Obelisk",
            "29": "Monolith",
            "11": "Ride to Valhalla"
        }
    },
    "33": {
        "name": "Kernel Keep",
        "links": {
            "34": "Kit Kennel ",
            "32": "Fox Burrow",
            "35": "Whetstones"
        }
    },
    "34": {
        "name": "Kit Kennel ",
        "links": {
            "29": "Monolith",
            "33": "Kernel Keep"
        }
    },
    "35": {
        "name": "Whetstones",
        "links": {
            "1": "Barrel Bluff",
            "33": "Kernel Keep"
        }
    }
}